jupyter_on_golem/__init__.py
jupyter_on_golem/__main__.py
jupyter_on_golem/golem.py
jupyter_on_golem/golem_kernel.py
jupyter_on_golem/manifest.json
jupyter_on_golem/remote_python.py
jupyter_on_golem-0.1.3.dist-info/LICENSE
jupyter_on_golem-0.1.3.dist-info/METADATA
jupyter_on_golem-0.1.3.dist-info/WHEEL
jupyter_on_golem-0.1.3.dist-info/RECORD
